oskar/__init__.py
oskar/_version.py
oskar/elasticity.py
oskar/elementMats.py
oskar/feaFunction.py
oskar/feaOp.py
oskar/feaSolution.py
oskar/feaSpace.py
oskar/linSolve.py
oskar/mathOp.py
oskar/mpatch.py
oskar/op.py
oskar/processes.py
oskar/solve.py
oskar/units.py
oskar/utils.py
oskar/tests/__init__.py
oskar/tests/closedForms.py
oskar/tests/test_00_misc.py
oskar/tests/test_01_assembling.py
oskar/tests/test_02_basic_equations.py
oskar/tests/test_03_linear_elasticity.py
oskar/tests/test_04_advection.py
oskar/tests/test_05_thm.py
oskar/tests/test_06_anisotropy.py
oskar/tests/test_07_mixed.py
oskar/tests/test_10_pde_expr.py
oskar/tests/utils.py
oskar-0.9.2.post1.dist-info/licenses/COPYING.md
oskar-0.9.2.post1.dist-info/METADATA
oskar-0.9.2.post1.dist-info/WHEEL
oskar-0.9.2.post1.dist-info/top_level.txt
oskar-0.9.2.post1.dist-info/RECORD
