Metadata-Version: 2.4
Name: oskar
Version: 0.9.2.post1
Summary: Finite element library with focus to THM coupled processes.
Author-email: carsten-forty2 <carsten-forty2@mailbox.org>
License-Expression: Apache-2.0
Project-URL: Homepage, https://gitlab.com/base-fn/oskar
Project-URL: Documentation, https://gitlab.com/base-fn/oskar
Project-URL: Repository, https://gitlab.com/base-fn/oskar
Project-URL: Bug Tracker, https://gitlab.com/base-fn/oskar/issues
Project-URL: Changelog, https://gitlab.com/base-fn/oskar/CHANGELOG.md
Keywords: finite element modelling
Classifier: Development Status :: 4 - Beta
Classifier: Programming Language :: Python
Classifier: Intended Audience :: Science/Research
Classifier: Programming Language :: Python :: 3 :: Only
Classifier: Topic :: Scientific/Engineering
Requires-Python: >=3.10
License-File: COPYING.md
Requires-Dist: pygimli>=2.0b
Requires-Dist: numpy>=2.1
Requires-Dist: matplotlib<3.10,>=3.7
Requires-Dist: scipy<1.15,>=1.14
Requires-Dist: sympy>=1.13
Requires-Dist: scooby
Requires-Dist: pyvista[all]
Requires-Dist: vtk>=9.4
Requires-Dist: pyqt5
Requires-Dist: tabulate
Requires-Dist: numdifftools
Provides-Extra: nb
Requires-Dist: jupyter; extra == "nb"
Requires-Dist: jupytext; extra == "nb"
Requires-Dist: voila; extra == "nb"
Requires-Dist: ipympl; extra == "nb"
Requires-Dist: dask; extra == "nb"
Requires-Dist: panel; extra == "nb"
Requires-Dist: ipywidgets_bokeh; extra == "nb"
Provides-Extra: test
Requires-Dist: tox; extra == "test"
Requires-Dist: ruff; extra == "test"
Requires-Dist: coverage[toml]; extra == "test"
Requires-Dist: pytest>=6.0; extra == "test"
Requires-Dist: pytest-cov; extra == "test"
Requires-Dist: pytest-html; extra == "test"
Requires-Dist: pytest-xdist; extra == "test"
Requires-Dist: pylint; extra == "test"
Requires-Dist: pybadges; extra == "test"
Requires-Dist: dask[distributed]; extra == "test"
Provides-Extra: doc
Requires-Dist: astroid==3.3.8; extra == "doc"
Requires-Dist: sphinx>=3.1; extra == "doc"
Requires-Dist: sphinxcontrib-bibtex; extra == "doc"
Requires-Dist: sphinxcontrib-programoutput; extra == "doc"
Requires-Dist: sphinxcontrib-doxylink; extra == "doc"
Requires-Dist: sphinxcontrib-svg2pdfconverter; extra == "doc"
Requires-Dist: sphinx-togglebutton; extra == "doc"
Requires-Dist: sphinx_copybutton; extra == "doc"
Requires-Dist: sphinx-gallery==0.16; extra == "doc"
Requires-Dist: sphinx-design; extra == "doc"
Requires-Dist: sphinx-autoapi<3.2,>=3.1; extra == "doc"
Requires-Dist: sphinx-mdinclude; extra == "doc"
Requires-Dist: sphinxext-opengraph; extra == "doc"
Requires-Dist: sphinx_toolbox; extra == "doc"
Requires-Dist: pydata-sphinx-theme==0.15.2; extra == "doc"
Requires-Dist: bibtexparser; extra == "doc"
Requires-Dist: myst_nb; extra == "doc"
Requires-Dist: pytexit; extra == "doc"
Requires-Dist: graphviz; extra == "doc"
Requires-Dist: linkify-it-py; extra == "doc"
Requires-Dist: sphinx_inline_tabs; extra == "doc"
Requires-Dist: jupytext; extra == "doc"
Provides-Extra: dev
Requires-Dist: oskar[doc,nb,test]; extra == "dev"
Requires-Dist: build; extra == "dev"
Requires-Dist: twine; extra == "dev"
Provides-Extra: all
Requires-Dist: oskar[dev]; extra == "all"
Dynamic: license-file
